Workbook

Sheet 1. Assumptions
B2: Tab 1 — ASSUMPTIONS / Giả định đầu vào
B3: Luật chơi: chỉ điền vào các ô MÀU VÀNG. Các ô khác là công thức và sẽ tự tính.
B5: 1. Product & Pricing / Sản phẩm & Giá
C6: Optimistic | D6: Base | E6: Pessimistic | F6: Đơn vị | G6: Ghi chú / Note
B7: ARPU — Giá bán bình quân/khách/tháng | C7: 180000 | D7: 150000 | E7: 130000 | F7: VND | G7: Pricing cao hơn → khó bán hơn nhưng margin tốt hơn
B8: Adoption rate — % TAM chuyển thành khách/tháng | C8: 0.02 | D8: 0.018 | E8: 0.012 | F8: %/tháng | G8: % TAM chuyển thành khách trả tiền mới mỗi tháng
B9: Total addressable market (số khách tiềm năng) | C9: 50000 | D9: 50000 | E9: 50000 | F9: khách | G9: Tổng số khách hàng tiềm năng có thể tiếp cận được
B11: 2. COGS / Chi phí biến đổi trên mỗi khách hàng
B12: API cost / khách / tháng | C12: 12000 | D12: 10000 | E12: 8000 | F12: VND | G12: Tiền gọi OpenAI/Anthropic/Gemini API
B13: Hidden costs (labeling, retraining, QA) | C13: 50000 | D13: 50000 | E13: 50000 | F13: VND | G13: Đừng quên! Đây là cục giết startup AI
B14: Infrastructure (server/cloud) / khách | C14: 5000 | D14: 10000 | E14: 10000 | F14: VND | G14: Phần allocate cloud cost cho mỗi khách
B15: → Tổng COGS / khách / tháng | C15: =C12+C13+C14 -> 67000 | D15: =D12+D13+D14 -> 70000 | E15: =E12+E13+E14 -> 68000
B17: 3. Customer Behavior / Hành vi khách hàng
B18: Monthly Churn Rate — % khách rời mỗi tháng | C18: 0.09 | D18: 0.1 | E18: 0.11 | F18: % | G18: Benchmark AI product < 5%/tháng
B19: → Số tháng ở lại trung bình | C19: =IFERROR(1/C18,0) -> 11.111111 | D19: =IFERROR(1/D18,0) -> 10 | E19: =IFERROR(1/E18,0) -> 9.0909091
B21: 4. Sales & Marketing / Chi phí thu hút khách
B22: CAC — Tổng chi phí có 1 khách hàng mới | C22: 40000 | D22: 40000 | E22: 20000 | F22: VND | G22: Tổng tiền Marketing & Sales / Số khách mới
B24: 5. Fixed Costs / Chi phí cố định hàng tháng
B25: Salaries — Lương team (PM/Dev/Designer) | C25: 300000000 | D25: 300000000 | E25: 150000000 | F25: VND/tháng | G25: Pessimistic = phải hire thêm nếu khó scale
B26: Office, tools, admin | C26: 30000000 | D26: 30000000 | E26: 15000000 | F26: VND/tháng
B27: Marketing budget hàng tháng | C27: 50000000 | D27: 50000000 | E27: 30000000 | F27: VND/tháng
B28: → Tổng Fixed Cost / tháng | C28: =SUM(C25:C27) -> 380000000 | D28: =SUM(D25:D27) -> 380000000 | E28: =SUM(E25:E27) -> 195000000
B30: 6. Initial Investment / Vốn đầu tư ban đầu
B31: Vốn đầu tư ban đầu (build MVP, setup) | C31: 400000000 | D31: 400000000 | E31: 300000000 | F31: VND | G31: Chi phí 1 lần — lương team build MVP, infrastructure setup
B32: Tiền mặt ban đầu (sau khi đã trừ vốn đầu tư) | C32: 1500000000 | D32: 1700000000 | E32: 1700000000 | F32: VND | G32: Số tiền có sẵn để chi trả fixed cost trong giai đoạn đầu
B34: 7. Discount Rate / Tỷ suất chiết khấu (cho NPV)
B35: Annual discount rate (WACC) | C35: 0.2 | D35: 0.2 | E35: 0.2 | F35: %/năm | G35: Mức kỳ vọng tối thiểu của nhà đầu tư cho dự án AI rủi ro
B36: → Monthly discount rate | C36: =(1+C35)^(1/12)-1 -> 0.01530947 | D36: =(1+D35)^(1/12)-1 -> 0.01530947 | E36: =(1+E35)^(1/12)-1 -> 0.01530947
B38: 8. Decision Note / Ghi chú quyết định
B39: ARPU 150.000 VNĐ vì nó là mức chi phí dễ chấp nhận cho các gia đình trung lưu đô thị trong khi vẫn đảm bảo biên lợi nhuận gộp trên 50% để bù đắp chi phí vận hành AI. Mức CAC 40.000 VNĐ được bảo vệ bởi chiến lược tiếp cận tập trung qua các hội nhóm cộng đồng caregiver và hợp tác với nhà thuốc, nơi có tỷ lệ chuyển đổi cao giúp tối ưu hóa chi phí quảng cáo so với việc chạy mass-marketing đại trà. Để bảo vệ con số này, dự án tập trung vào mức CAC 40.000 VNĐ thông qua chiến lược thâm nhập vào cộng đồng caregiver thông qua mạng xã hội và mạng lưới nhà thuốc thay vì đổ tiền vào quảng cáo đại trà để đạt tỷ lệ chuyển đổi cao với chi phí tối ưu. Dù Hidden Costs (chi phí dán nhãn dữ liệu, QA,chuyên gia ) hiện là rủi ro biến phí lớn nhất. Trong kịch bản tốt, dữ liệu tích lũy đủ lớn, AI sẽ dần tự động hóa quy trình kiểm định, giúp giảm phụ thuộc vào nhân sự thủ công và tối ưu hóa chi phí gọi API. Kết hợp với hiệu ứng lan tỏa từ cộng đồng, biên lợi nhuận sẽ được mở rộng theo thời gian, chuyển đổi mô hình từ thâm dụng lao động sang khai thác hiệu suất thuật toán thuần túy.

Sheet 3. P&L & ROI
B2: Tab 3 — P&L & ROI / 24 tháng
B4: Chọn scenario: | C4: Pessimistic | D4: Đổi scenario tại đây để toàn bộ P&L tự cập nhật
B6: Active scenario index: | C6: =MATCH(C4,{"Optimistic","Base","Pessimistic"},0) -> 3
B7: Selected scenario inputs ↓
B8: ARPU / khách / tháng | C8: =CHOOSE($C$6,'1. Assumptions'!C7,'1. Assumptions'!D7,'1. Assumptions'!E7) -> 130000
B9: Adoption rate | C9: =CHOOSE($C$6,'1. Assumptions'!C8,'1. Assumptions'!D8,'1. Assumptions'!E8) -> 0.012
B10: TAM (số khách tiềm năng) | C10: =CHOOSE($C$6,'1. Assumptions'!C9,'1. Assumptions'!D9,'1. Assumptions'!E9) -> 50000
B11: Total COGS / khách | C11: =CHOOSE($C$6,'1. Assumptions'!C15,'1. Assumptions'!D15,'1. Assumptions'!E15) -> 68000
B12: Monthly Churn Rate | C12: =CHOOSE($C$6,'1. Assumptions'!C18,'1. Assumptions'!D18,'1. Assumptions'!E18) -> 0.11
B13: CAC / khách mới | C13: =CHOOSE($C$6,'1. Assumptions'!C22,'1. Assumptions'!D22,'1. Assumptions'!E22) -> 20000
B14: Fixed Cost / tháng | C14: =CHOOSE($C$6,'1. Assumptions'!C28,'1. Assumptions'!D28,'1. Assumptions'!E28) -> 195000000
B15: Initial Investment | C15: =CHOOSE($C$6,'1. Assumptions'!C31,'1. Assumptions'!D31,'1. Assumptions'!E31) -> 300000000
B16: Initial Cash | C16: =CHOOSE($C$6,'1. Assumptions'!C32,'1. Assumptions'!D32,'1. Assumptions'!E32) -> 1700000000
B17: Monthly Discount Rate | C17: =CHOOSE($C$6,'1. Assumptions'!C36,'1. Assumptions'!D36,'1. Assumptions'!E36) -> 0.01530947
B20: P&L Projection — 24 months (VND)
B21: Month | C21: M1 | D21: M2 | E21: M3 | F21: M4 | G21: M5 | H21: M6 | I21: M7 | J21: M8 | K21: M9 | L21: M10 | M21: M11 | N21: M12 | O21: M13 | P21: M14 | Q21: M15 | R21: M16 | S21: M17 | T21: M18 | U21: M19 | V21: M20 | W21: M21 | X21: M22 | Y21: M23 | Z21: M24 | AA21: TOTAL
B22: New customers acquired | C22: =ROUND($C$10*$C$9,0) -> 600 | D22: =ROUND($C$10*$C$9,0) -> 600 | E22: =ROUND($C$10*$C$9,0) -> 600 | F22: =ROUND($C$10*$C$9,0) -> 600 | G22: =ROUND($C$10*$C$9,0) -> 600 | H22: =ROUND($C$10*$C$9,0) -> 600 | I22: =ROUND($C$10*$C$9,0) -> 600 | J22: =ROUND($C$10*$C$9,0) -> 600 | ... Z22: =ROUND($C$10*$C$9,0) -> 600 | AA22: =SUM(C22:Z22) -> 14400
B23: Active customers (end of month) | C23: =C22 -> 600 | D23: =C23*(1-$C$12)+D22 -> 1134 | E23: =D23*(1-$C$12)+E22 -> 1609.26 | F23: =E23*(1-$C$12)+F22 -> 2032.2414 | G23: =F23*(1-$C$12)+G22 -> 2408.6948 | H23: =G23*(1-$C$12)+H22 -> 2743.7384 | I23: =H23*(1-$C$12)+I22 -> 3041.9272 | J23: =I23*(1-$C$12)+J22 -> 3307.3152 | K23: =J23*(1-$C$12)+K22 -> 3543.5105 | ... Z23: =Y23*(1-$C$12)+Z22 -> 5121.7949
B25: Revenue | C25: =C23*$C$8 -> 78000000 | D25: =D23*$C$8 -> 147420000 | E25: =E23*$C$8 -> 209203800 | F25: =F23*$C$8 -> 264191382 | G25: =G23*$C$8 -> 3.1313033e+08 | H25: =H23*$C$8 -> 3.5668599e+08 | I25: =I23*$C$8 -> 3.9545053e+08 | J25: =J23*$C$8 -> 4.2995098e+08 | ... Z25: =Z23*$C$8 -> 6.6583334e+08 | AA25: =SUM(C25:Z25) -> 1.1630985e+10
B26: COGS (variable cost) | C26: =C23*$C$11 -> 40800000 | D26: =D23*$C$11 -> 77112000 | E26: =E23*$C$11 -> 109429680 | F26: =F23*$C$11 -> 1.3819242e+08 | G26: =G23*$C$11 -> 1.6379125e+08 | H26: =H23*$C$11 -> 1.8657421e+08 | I26: =I23*$C$11 -> 2.0685105e+08 | J26: =J23*$C$11 -> 2.2489743e+08 | ... Z26: =Z23*$C$11 -> 3.4828206e+08 | AA26: =SUM(C26:Z26) -> 6.0838997e+09
B27: Gross Profit | C27: =C25-C26 -> 37200000 | D27: =D25-D26 -> 70308000 | E27: =E25-E26 -> 99774120 | F27: =F25-F26 -> 1.2599897e+08 | G27: =G25-G26 -> 1.4933908e+08 | H27: =H25-H26 -> 1.7011178e+08 | I27: =I25-I26 -> 1.8859949e+08 | J27: =J25-J26 -> 2.0505354e+08 | ... Z27: =Z25-Z26 -> 3.1755129e+08 | AA27: =SUM(C27:Z27) -> 5.547085e+09
B28: Marketing/Acquisition cost | C28: =C22*$C$13 -> 12000000 | D28: =D22*$C$13 -> 12000000 | E28: =E22*$C$13 -> 12000000 | F28: =F22*$C$13 -> 12000000 | G28: =G22*$C$13 -> 12000000 | H28: =H22*$C$13 -> 12000000 | I28: =I22*$C$13 -> 12000000 | J28: =J22*$C$13 -> 12000000 | ... Z28: =Z22*$C$13 -> 12000000 | AA28: =SUM(C28:Z28) -> 288000000
B29: Fixed cost (salaries + ops) | C29: =$C$14 -> 195000000 | D29: =$C$14 -> 195000000 | E29: =$C$14 -> 195000000 | F29: =$C$14 -> 195000000 | G29: =$C$14 -> 195000000 | H29: =$C$14 -> 195000000 | I29: =$C$14 -> 195000000 | J29: =$C$14 -> 195000000 | ... Z29: =$C$14 -> 195000000 | AA29: =SUM(C29:Z29) -> 4680000000
B30: Operating Profit (EBITDA) | C30: =C27-C28-C29 -> -169800000 | D30: =D27-D28-D29 -> -136692000 | E30: =E27-E28-E29 -> -107225880 | F30: =F27-F28-F29 -> -81001033 | G30: =G27-G28-G29 -> -57660920 | H30: =H27-H28-H29 -> -36888218 | I30: =I27-I28-I29 -> -18400514 | J30: =J27-J28-J29 -> -1946457.8 | ... Z30: =Z27-Z28-Z29 -> 1.1055129e+08 | AA30: =SUM(C30:Z30) -> 5.7908504e+08
B32: Cash Flow (after investment) | C32: =C30-$C$15 -> -469800000 | D32: =D30 -> -136692000 | E32: =E30 -> -107225880 | F32: =F30 -> -81001033 | G32: =G30 -> -57660920 | H32: =H30 -> -36888218 | I32: =I30 -> -18400514 | J32: =J30 -> -1946457.8 | K32: =K30 -> 12697653 | ... Z32: =Z30 -> 1.1055129e+08 | AA32: =SUM(C32:Z32) -> 2.7908504e+08
B33: Cash Position (cumulative) | C33: =$C$16+C32 -> 1230200000 | D33: =C33+D32 -> 1093508000 | E33: =D33+E32 -> 986282120 | F33: =E33+F32 -> 9.0528109e+08 | G33: =F33+G32 -> 8.4762017e+08 | H33: =G33+H32 -> 8.1073195e+08 | I33: =H33+I32 -> 7.9233143e+08 | J33: =I33+J32 -> 7.9038498e+08 | K33: =J33+K32 -> 8.0308263e+08 | ... Z33: =Y33+Z32 -> 1.979085e+09
B36: ROI Metrics / Chỉ số đánh giá tổng thể dự án
B37: NPV (Net Present Value, mil VND) | C37: =(NPV($C$17,D32:Z32)+C32)/1000000 -> 22.920884 | D37: ="(target: > 0)" -> (target: > 0)
B38: IRR (Annual) | C38: =IFERROR((1+IRR(C32:Z32))^12-1,0) -> 0.22328485 | D38: ="(target: > "&TEXT(CHOOSE($C$6,'1. Assumptions'!C35,'1. Assumptions'!D35,'1. Assumptions'!E35),"0.0%")&")" -> (target: > 20.0%)
B39: Project Payback (months) | C39: =IFERROR(MATCH(TRUE(),INDEX(C41:Z41>=0,0),0),"> 24") -> 22 | D39: ="(target: < 24)" -> (target: < 24)
B40: Runway (months until cash = 0) | C40: =IFERROR(MATCH(TRUE(),INDEX(C33:Z33<0,0),0)-1,">= 24") -> >= 24 | D40: ="(target: >= 12)" -> (target: >= 12)
B41: (helper: cumulative cash flow) | C41: =C32 -> -469800000 | D41: =C41+D32 -> -606492000 | E41: =D41+E32 -> -713717880 | F41: =E41+F32 -> -7.9471891e+08 | G41: =F41+G32 -> -8.5237983e+08 | H41: =G41+H32 -> -8.8926805e+08 | I41: =H41+I32 -> -9.0766857e+08 | J41: =I41+J32 -> -9.0961502e+08 | K41: =J41+K32 -> -8.9691737e+08 | ... Z41: =Y41+Z32 -> 2.7908504e+08
B43: Final Verdict / Có nên làm dự án này?
B44: Project Decision | C44: =IF(AND(C37>0,C38>CHOOSE($C$6,'1. Assumptions'!C35,'1. Assumptions'!D35,'1. Assumptions'!E35)),"✓ GO — NPV+ và IRR > WACC",IF(C37<0,"✗ NO-GO — NPV âm: dự án không tạo giá trị","⚠ HOLD — IRR thấp hơn kỳ vọng, cần điều chỉnh")) -> ✓ GO — NPV+ và IRR > WACC

Sheet 2. Unit Economics
B2: Tab 2 — UNIT ECONOMICS / Kinh tế đơn vị
B3: Tự động tính từ Tab 1. Kiểm tra: LTV/CAC > 3 (Base) và CAC Payback < 12 tháng.
B5: Chỉ số | C5: Optimistic | D5: Base | E5: Pessimistic | F5: Đơn vị | G5: Benchmark / Note
B7: Trên mỗi khách hàng / per customer
B8: ARPU / tháng | C8: ='1. Assumptions'!C7 -> 180000 | D8: ='1. Assumptions'!D7 -> 150000 | E8: ='1. Assumptions'!E7 -> 130000 | F8: VND | G8: Liên kết từ Tab Assumptions
B9: COGS / tháng | C9: ='1. Assumptions'!C15 -> 67000 | D9: ='1. Assumptions'!D15 -> 70000 | E9: ='1. Assumptions'!E15 -> 68000 | F9: VND
B10: → Gross Profit / tháng | C10: =C8-C9 -> 113000 | D10: =D8-D9 -> 80000 | E10: =E8-E9 -> 62000
B11: → Gross Margin % | C11: =IFERROR(C10/C8,0) -> 0.62777778 | D11: =IFERROR(D10/D8,0) -> 0.53333333 | E11: =IFERROR(E10/E8,0) -> 0.47692308 | G11: AI product target: 40-60%. SaaS truyền thống: 80%+
B13: LTV — Customer Lifetime Value
B14: Số tháng ở lại trung bình | C14: ='1. Assumptions'!C19 -> 11.111111 | D14: ='1. Assumptions'!D19 -> 10 | E14: ='1. Assumptions'!E19 -> 9.0909091 | F14: tháng
B15: → LTV = Gross Profit × Số tháng ở lại | C15: =C10*C14 -> 1255555.6 | D15: =D10*D14 -> 800000 | E15: =E10*E14 -> 563636.36 | G15: Tổng lợi nhuận gộp một khách mang lại trong vòng đời
B17: CAC — Customer Acquisition Cost
B18: CAC — Chi phí thu hút 1 khách | C18: ='1. Assumptions'!C22 -> 40000 | D18: ='1. Assumptions'!D22 -> 40000 | E18: ='1. Assumptions'!E22 -> 20000 | F18: VND
B20: Key Ratios / Tỷ lệ then chốt
B21: → LTV / CAC Ratio | C21: =IFERROR(C15/C18,0) -> 31.388889 | D21: =IFERROR(D15/D18,0) -> 20 | E21: =IFERROR(E15/E18,0) -> 28.181818 | G21: 🎯 Target > 3.0x (tiêu chuẩn vàng VC)
B22: → CAC Payback Period | C22: =IFERROR(C18/C10,0) -> 0.3539823 | D22: =IFERROR(D18/D10,0) -> 0.5 | E22: =IFERROR(E18/E10,0) -> 0.32258065 | G22: 🎯 Target < 12 tháng (early-stage)
B24: Verdict / Kết luận
B25: Unit Economics Status | C25: =IF(AND(C21>=3,C22<=12),"✓ HEALTHY",IF(OR(C21<1,C22>18),"✗ UNHEALTHY","⚠ WATCH")) -> ✓ HEALTHY | D25: =IF(AND(D21>=3,D22<=12),"✓ HEALTHY",IF(OR(D21<1,D22>18),"✗ UNHEALTHY","⚠ WATCH")) -> ✓ HEALTHY | E25: =IF(AND(E21>=3,E22<=12),"✓ HEALTHY",IF(OR(E21<1,E22>18),"✗ UNHEALTHY","⚠ WATCH")) -> ✓ HEALTHY
